common/__init__.py
common/color.py
common/img.py
common/state.py
common/test_utils.py
common/img/title_card.png
kitty_common-0.5.6.dist-info/licenses/LICENSE
kitty_common-0.5.6.dist-info/METADATA
kitty_common-0.5.6.dist-info/WHEEL
kitty_common-0.5.6.dist-info/top_level.txt
kitty_common-0.5.6.dist-info/RECORD
